{
  "$schema": "../gen/schemas/desktop-schema.json",
  "identifier": "default",
  "description": "Capability for the main window",
  "windows": [
    "main"
  ],
  "permissions": [
    "core:default",
    "opener:default",
    "clipboard-manager:default",
    "clipboard-manager:allow-write-text",
    "clipboard-manager:allow-read-text",
    "deep-link:default",
    "store:default",
    "core:window:allow-toggle-maximize",
    "core:window:allow-start-dragging",
    "http:default",
    {
      "identifier": "http:allow-fetch",
      "allow": [
        { "url": "https://pod-server.ghost-spica.ts.net/*" },
        { "url": "https://document-server-as95.onrender.com/*" },
        { "url": "https://frog-server-q36c.onrender.com/*" },
        { "url": "http://localhost:3000/*" },
        { "url": "http://localhost:3001/*" }
      ]
    },
    "http:allow-fetch-cancel",
    "http:allow-fetch-read-body",
    "http:allow-fetch-send",
    "fs:allow-read-text-file",
    "dialog:default"
  ]
}
